spkan/__init__.py
spkan/conv.py
spkan/cuda_tools.py
spkan/tests.py
spkan/modules/second_neck.py
spkan/ops/__init__.py
spkan/ops/bsplines.cu
spkan/ops/bsplines_g.cpp
spkan/ops/setup.py
spkan-0.0.2a4.dist-info/LICENSE
spkan-0.0.2a4.dist-info/METADATA
spkan-0.0.2a4.dist-info/WHEEL
spkan-0.0.2a4.dist-info/top_level.txt
spkan-0.0.2a4.dist-info/RECORD
