Metadata-Version: 2.1
Name: spkan
Version: 0.0.2a4
Summary: A drop-in replacement for sparse convolutions using Kolmogorov-Arnold Networks
Author-email: "Mellon M. Zhang" <meilongz@gatech.edu>
Project-URL: Homepage, https://github.com/meilongzhang/spkan
Project-URL: Issues, https://github.com/meilongzhang/spkan/issues
Keywords: kan,sparse,convolutions,kolmogorov-arnold,submanifold
Classifier: Programming Language :: Python :: 3.9
Classifier: Programming Language :: Python :: 3.8
Classifier: Programming Language :: Python :: 3.7
Classifier: License :: OSI Approved :: MIT License
Classifier: Operating System :: OS Independent
Requires-Python: >=3.7
License-File: LICENSE
